wide/__init__.py
wide/empca.py
wide/fuzzy_lda.py
wide/nca.py
wide/sompy.py
wide/tsne.py
wide-0.0.1.dist-info/LICENSE
wide-0.0.1.dist-info/METADATA
wide-0.0.1.dist-info/WHEEL
wide-0.0.1.dist-info/top_level.txt
wide-0.0.1.dist-info/RECORD
